LICENSE.txt
MANIFEST.in
NOTICE.txt
README.txt
setup.cfg
setup.py
src/cmislib/__init__.py
src/cmislib/cmis_services.py
src/cmislib/domain.py
src/cmislib/exceptions.py
src/cmislib/messages.py
src/cmislib/model.py
src/cmislib/net.py
src/cmislib/util.py
src/cmislib/atompub/__init__.py
src/cmislib/atompub/binding.py
src/cmislib/browser/__init__.py
src/cmislib/browser/binding.py
src/cmislib3.egg-info/PKG-INFO
src/cmislib3.egg-info/SOURCES.txt
src/cmislib3.egg-info/dependency_links.txt
src/cmislib3.egg-info/requires.txt
src/cmislib3.egg-info/top_level.txt