Metadata-Version: 1.1
Name: cmislib3
Version: 1.0.6
Summary: Apache Chemistry CMIS client library for Python 3
Home-page: https://github.com/luca-92/cmislib3
Author: Luca Marchetti, Apache Chemistry Project
Author-email: dev@chemistry.apache.org, marchetti.luca.1992@gmail.com
License: Apache License (2.0)
Platform: UNKNOWN
Classifier: Development Status :: 4 - Beta
Classifier: Intended Audience :: Developers
Classifier: License :: OSI Approved :: Apache Software License
Classifier: Operating System :: OS Independent
Classifier: Programming Language :: Python
Classifier: Topic :: Software Development :: Libraries
